UA_GuardedSettings/__init__.py
UA_GuardedSettings/guardedsettings.py
ua_guardedsettings-0.4.0.dist-info/LICENSE
ua_guardedsettings-0.4.0.dist-info/WHEEL
ua_guardedsettings-0.4.0.dist-info/METADATA
ua_guardedsettings-0.4.0.dist-info/RECORD
