Metadata-Version: 2.1
Name: UA_GuardedSettings
Version: 0.4.0
Summary: Insert content from JSON into Django settings.py
Author-email: Gunnar Swan <gunnar.swan@yahoo.com>
Requires-Python: >=3.6
Classifier: Framework :: Django
